Metadata-Version: 2.4
Name: python-lsp-server
Version: 1.13.0
Summary: Python Language Server for the Language Server Protocol
Author: Python Language Server Contributors
License: MIT
Project-URL: Homepage, https://github.com/python-lsp/python-lsp-server
Requires-Python: >=3.9
License-File: LICENSE
Requires-Dist: docstring-to-markdown
Requires-Dist: importlib_metadata>=4.8.3; python_version < "3.10"
Requires-Dist: jedi<0.20.0,>=0.17.2
Requires-Dist: pluggy>=1.0.0
Requires-Dist: python-lsp-jsonrpc<2.0.0,>=1.1.0
Requires-Dist: ujson>=3.0.0
Requires-Dist: black
Provides-Extra: all
Requires-Dist: autopep8<2.1.0,>=2.0.4; extra == "all"
Requires-Dist: flake8<8,>=7.1; extra == "all"
Requires-Dist: mccabe<0.8.0,>=0.7.0; extra == "all"
Requires-Dist: pycodestyle<2.13.0,>=2.12.0; extra == "all"
Requires-Dist: pydocstyle<6.4.0,>=6.3.0; extra == "all"
Requires-Dist: pyflakes<3.3.0,>=3.2.0; extra == "all"
Requires-Dist: pylint<4,>=3.1; extra == "all"
Requires-Dist: rope>=1.11.0; extra == "all"
Requires-Dist: yapf>=0.33.0; extra == "all"
Requires-Dist: whatthepatch<2.0.0,>=1.0.2; extra == "all"
Provides-Extra: autopep8
Requires-Dist: autopep8<2.1.0,>=2.0.4; extra == "autopep8"
Provides-Extra: flake8
Requires-Dist: flake8<8,>=7.1; extra == "flake8"
Provides-Extra: mccabe
Requires-Dist: mccabe<0.8.0,>=0.7.0; extra == "mccabe"
Provides-Extra: pycodestyle
Requires-Dist: pycodestyle<2.13.0,>=2.12.0; extra == "pycodestyle"
Provides-Extra: pydocstyle
Requires-Dist: pydocstyle<6.4.0,>=6.3.0; extra == "pydocstyle"
Provides-Extra: pyflakes
Requires-Dist: pyflakes<3.3.0,>=3.2.0; extra == "pyflakes"
Provides-Extra: pylint
Requires-Dist: pylint<4,>=3.1; extra == "pylint"
Provides-Extra: rope
Requires-Dist: rope>=1.11.0; extra == "rope"
Provides-Extra: yapf
Requires-Dist: yapf>=0.33.0; extra == "yapf"
Requires-Dist: whatthepatch<2.0.0,>=1.0.2; extra == "yapf"
Provides-Extra: websockets
Requires-Dist: websockets>=10.3; extra == "websockets"
Provides-Extra: test
Requires-Dist: pylint<4,>=3.1; extra == "test"
Requires-Dist: pytest; extra == "test"
Requires-Dist: pytest-cov; extra == "test"
Requires-Dist: coverage; extra == "test"
Requires-Dist: numpy; extra == "test"
Requires-Dist: pandas; extra == "test"
Requires-Dist: matplotlib; extra == "test"
Requires-Dist: pyqt5; extra == "test"
Requires-Dist: flaky; extra == "test"
Requires-Dist: websockets>=10.3; extra == "test"
Dynamic: license-file
